[
  {
    "name": "Hardened",
    "prefix": "Hardened",
    "weaponType": "Small Guns",
    "type": "Receiver",
    "damageChange": 1,
    "weightChange": 0,
    "costChange": 20,
    "perks": []
  },
  {
    "name": "Powerful",
    "prefix": "Powerful",
    "weaponType": "Small Guns",
    "type": "Receiver",
    "damageChange": 2,
    "weightChange": 1,
    "costChange": 25,
    "perks": ["Gun Nut 1"]
  },
  {
    "name": "Advanced",
    "prefix": "Advanced",
    "weaponType": "Small Guns",
    "type": "Receiver",
    "damageChange": 3,
    "fireRateChange": 1,
    "weightChange": 2,
    "costChange": 35,
    "perks": ["Gun Nut 2"]
  },
  {
    "name": "Calibrated",
    "prefix": "Calibrated",
    "weaponType": "Small Guns",
    "type": "Receiver",
    "weightChange": 0,
    "gainedEffects": ["Vicious"],
    "costChange": 25,
    "perks": []
  },
  {
    "name": "Automatic",
    "prefix": "Auto",
    "weaponType": "Small Guns",
    "type": "Receiver",
    "damageChange": -1,
    "fireRateChange": 2,
    "gainedQualities": ["Inaccurate"],
    "gainedEffects": ["Burst"],
    "weightChange": 1,
    "costChange": 30,
    "perks": ["Gun Nut 1"]
  },
  {
    "name": "Hair Trigger",
    "prefix": "Hair Trigger",
    "weaponType": "Small Guns",
    "type": "Receiver",
    "fireRateChange": 1,
    "weightChange": 0,
    "costChange": 20,
    "perks": ["Gun Nut 2"]
  },
  {
    "name": ".38 Receiver",
    "prefix": ".38 ",
    "weaponType": "Small Guns",
    "type": "Receiver",
    "fixDamage": 4,
    "ammo": ".38",
    "weightChange": 3,
    "costChange": 20,
    "perks": ["Gun Nut 4"]
  },
  {
    "name": ".308 Receiver",
    "prefix": ".308",
    "weaponType": "Small Guns",
    "type": "Receiver",
    "fixDamage": 7,
    "ammo": ".308",
    "weightChange": 4,
    "costChange": 40,
    "perks": ["Gun Nut 4"]
  },
  {
    "name": ".45 Receiver",
    "prefix": ".45",
    "weaponType": "Small Guns",
    "type": "Receiver",
    "fixDamage": 4,
    "fireRateChange": 1,
    "ammo": ".45",
    "weightChange": 2,
    "costChange": 19,
    "perks": ["Gun Nut 2"]
  },
  {
    "name": ".50 Receiver",
    "prefix": ".50",
    "weaponType": "Small Guns",
    "type": "Receiver",
    "fixDamage": 8,
    "gainedEffects": ["Vicious"],
    "ammo": ".50",
    "weightChange": 4,
    "costChange": 30,
    "perks": ["Gun Nut 4"]
  },
  {
    "name": "Automatic Piston",
    "prefix": "Automatic",
    "weaponType": "Small Guns",
    "type": "Receiver",
    "fireRateChange": 2,
    "rangeChange": -1,
    "weightChange": 2,
    "costChange": 75,
    "perks": ["Gun Nut 2"]
  },
  {
    "name": "Snubnose Barrel",
    "prefix": "Snub-noses",
    "weaponType": "Small Guns",
    "type": "Barrel",
    "gainedQualities": ["Inaccurate"],
    "weightChange": -1,
    "costChange": 0,
    "perks": []
  },
  {
    "name": "Bull Barrel",
    "prefix": "Bull Barrel",
    "weaponType": "Small Guns",
    "type": "Barrel",
    "gainedQualities": ["Reliable"],
    "weightChange": 0,
    "costChange": 10,
    "perks": ["Gun Nut 3"]
  },
  {
    "name": "Long Barrel",
    "prefix": "Long",
    "weaponType": "Small Guns",
    "type": "Barrel",
    "rangeChange": 1,
    "weightChange": 1,
    "costChange": 20,
    "perks": ["Gun Nut 1"]
  },
  {
    "name": "Ported Barrel",
    "prefix": "Ported",
    "weaponType": "Small Guns",
    "type": "Barrel",
    "rangeChange": 1,
    "fireRateChange": 1,
    "weightChange": 1,
    "costChange": 35,
    "perks": ["Gun Nut 4"]
  },
  {
    "name": "Vented Barrel",
    "prefix": "Vented",
    "weaponType": "Small Guns",
    "type": "Barrel",
    "rangeChange": 1,
    "fireRateChange": 1,
    "gainedQualities": ["Reliable"],
    "weightChange": 1,
    "costChange": 36,
    "perks": ["Gun Nut 4"]
  },
  {
    "name": "Sawed-Off Barrel",
    "prefix": "Sawed-Off",
    "weaponType": "Small Guns",
    "type": "Barrel",
    "removedQualities": ["Two-Handed"],
    "gainedQualities": ["Close Quarters"],
    "weightChange": -2,
    "costChange": 3,
    "perks": []
  },
  {
    "name": "Finned Barrel",
    "prefix": "Finned",
    "weaponType": "Small Guns",
    "type": "Barrel",
    "damageChange": 1,
    "rangeChange": 1,
    "weightChange": 2,
    "costChange": 15,
    "perks": ["Gun Nut 2"]
  },
  {
    "name": "Comfort Grip",
    "prefix": "Comfort",
    "weaponType": "Small Guns",
    "type": "Grip",
    "removedQualities": ["Inaccurate"],
    "weightChange": 0,
    "costChange": 6,
    "perks": []
  },
  {
    "name": "Sharpshooter’s Grip",
    "prefix": "Sharpshooter’s",
    "weaponType": "Small Guns",
    "type": "Grip",
    "removedQualities": ["Inaccurate"],
    "gainedEffects": ["Piercing 1"],
    "weightChange": 0,
    "costChange": 10,
    "perks": ["Gun Nut 1"]
  },
  {
    "name": "Full Stock",
    "prefix": "",
    "weaponType": "Small Guns",
    "type": "Stock",
    "gainedQualities": ["Two-Handed"],
    "removedQualities": ["Inaccurate"],
    "weightChange": 1,
    "costChange": 10,
    "perks": []
  },
  {
    "name": "Marksman’s Stock",
    "prefix": "Marksman’s",
    "weaponType": "Small Guns",
    "type": "Stock",
    "gainedQualities": ["Two-Handed", "Accurate"],
    "removedQualities": ["Inaccurate"],
    "weightChange": 2,
    "costChange": 20,
    "perks": ["Gun Nut 2"]
  },
  {
    "name": "Recoil Compensating Stock",
    "prefix": "Recoil Compensated",
    "weaponType": "Small Guns",
    "type": "Stock",
    "fireRateChange": 1,
    "gainedQualities": ["Two-Handed"],
    "removedQualities": ["Inaccurate"],
    "weightChange": 2,
    "costChange": 3,
    "perks": ["Gun Nut 3"]
  },
  {
    "name": "Reflex Sight",
    "prefix": "Tactical",
    "weaponType": "Small Guns",
    "type": "Sight",
    "effects": "May re-roll hit location die",
    "weightChange": 0,
    "costChange": 14,
    "perks": []
  },
  {
    "name": "Short Scope",
    "prefix": "Scoped",
    "weaponType": "Small Guns",
    "type": "Sight",
    "gainedQualities": ["Accurate"],
    "weightChange": 1,
    "costChange": 11,
    "perks": []
  },
  {
    "name": "Long Scope",
    "prefix": "Scoped",
    "weaponType": "Small Guns",
    "type": "Sight",
    "rangeChange": 1,
    "gainedQualities": ["Accurate"],
    "weightChange": 1,
    "costChange": 29,
    "perks": ["Science! 2"]
  },
  {
    "name": "Short Night Vision Scope",
    "prefix": "Night Vision",
    "weaponType": "Small Guns",
    "type": "Sight",
    "gainedQualities": ["Accurate", "Night Vision"],
    "weightChange": 1,
    "costChange": 38,
    "perks": ["Science! 2"]
  },
  {
    "name": "Long Night Vision Scope",
    "prefix": "Night Vision",
    "weaponType": "Small Guns",
    "type": "Sight",
    "rangeChange": 1,
    "gainedQualities": ["Accurate", "Night Vision"],
    "weightChange": 1,
    "costChange": 50,
    "perks": ["Science! 3"]
  },
  {
    "name": "Recon Scope",
    "prefix": "Recon",
    "weaponType": "Small Guns",
    "type": "Sight",
    "gainedQualities": ["Accurate", "Recon"],
    "weightChange": 1,
    "costChange": 59,
    "perks": ["Science! 3"]
  },
  {
    "name": "Bayonet",
    "prefix": "Bayoneted",
    "weaponType": "Small Guns",
    "type": "Muzzle",
    "fixDamage": 4,
    "effects": "As a Melee weapon, deals 4CD Piercing 1 Physical damage",
    "weightChange": 2,
    "costChange": 10,
    "perks": []
  },
  {
    "name": "Compensator",
    "prefix": "Compensated",
    "weaponType": "Small Guns",
    "type": "Muzzle",
    "removedQualities": ["Inaccurate"],
    "weightChange": 1,
    "costChange": 15,
    "perks": ["Gun Nut 1"]
  },
  {
    "name": "Muzzle Break",
    "prefix": "Muzzled",
    "weaponType": "Small Guns",
    "type": "Muzzle",
    "fireRateChange": 1,
    "removedQualities": ["Inaccurate"],
    "weightChange": 1,
    "costChange": 30,
    "perks": ["Gun Nut 1"]
  },
  {
    "name": "Suppressor",
    "prefix": "Suppressed",
    "weaponType": "Small Guns",
    "type": "Muzzle",
    "gainedQualities": ["Suppressed"],
    "weightChange": 2,
    "costChange": 45,
    "perks": ["Gun Nut 2"]
  },
  {
    "name": "Beta Wave Tuner",
    "prefix": "Incendiary",
    "weaponType": "Energy Weapon",
    "type": "Capacitor",
    "gainedEffects": ["Persistent"],
    "weightChange": 0,
    "costChange": 30,
    "perks": []
  },
  {
    "name": "Boosted Capacitor",
    "prefix": "Boosted",
    "weaponType": "Energy Weapon",
    "type": "Capacitor",
    "damageChange": 1,
    "fireRateChange": -1,
    "weightChange": 0,
    "costChange": 35,
    "perks": []
  },
  {
    "name": "Photon Exciter",
    "prefix": "Excited",
    "weaponType": "Energy Weapon",
    "type": "Capacitor",
    "gainedEffects": ["Vicious"],
    "weightChange": 0,
    "costChange": 30,
    "perks": ["Science! 1"]
  },
  {
    "name": "Photon Agitator",
    "prefix": "Agitated",
    "weaponType": "Energy Weapon",
    "type": "Capacitor",
    "damageChange": 1,
    "gainedEffects": ["Vicious"],
    "weightChange": 1,
    "costChange": 35,
    "perks": ["Science! 2"]
  },
  {
    "name": "Three-Crank Capacitor (Laser Musket)",
    "prefix": "Three-crank",
    "weaponType": "Energy Weapon",
    "type": "Capacitor",
    "damageChange": 1,
    "effects": "consumes 3 shots per attack",
    "weightChange": 0,
    "costChange": 4,
    "perks": []
  },
  {
    "name": "Four-Crank Capacitor (Laser Musket)",
    "prefix": "Four-crank",
    "weaponType": "Energy Weapon",
    "type": "Capacitor",
    "damageChange": 2,
    "effects": "consumes 4 shots per attack",
    "weightChange": 1,
    "costChange": 8,
    "perks": ["Science! 1"]
  },
  {
    "name": "Five-Crank Capacitor (Laser Musket)",
    "prefix": "Five-crank",
    "weaponType": "Energy Weapon",
    "type": "Capacitor",
    "damageChange": 3,
    "effects": "consumes 5 shots per attack",
    "weightChange": 1,
    "costChange": 12,
    "perks": ["Science! 2"]
  },
  {
    "name": "Six-Crank Capacitor (Laser Musket)",
    "prefix": "Six-crank",
    "weaponType": "Energy Weapon",
    "type": "Capacitor",
    "damageChange": 4,
    "effects": "consumes 6 shots per attack",
    "weightChange": 2,
    "costChange": 16,
    "perks": ["Science! 3"]
  },
  {
    "name": "Bracketed Short Barrel",
    "prefix": "",
    "weaponType": "Energy Weapon",
    "type": "Barrel",
    "effects": "Allows the weapon to take a Muzzle mod",
    "weightChange": 0,
    "costChange": 6,
    "perks": []
  },
  {
    "name": "Long Barrel",
    "prefix": "Long",
    "weaponType": "Energy Weapon",
    "type": "Barrel",
    "rangeChange": 1,
    "removedQualities": ["Close Quarters"],
    "weightChange": 2,
    "costChange": 20,
    "perks": []
  },
  {
    "name": "Splitter",
    "prefix": "Scattergun",
    "weaponType": "Energy Weapon",
    "type": "Barrel",
    "damageChange": -1,
    "gainedEffects": ["Spread"],
    "gainedQualities": ["Inaccurate"],
    "weightChange": 1,
    "costChange": 31,
    "perks": []
  },
  {
    "name": "Automatic Barrel",
    "prefix": "Automatic",
    "weaponType": "Energy Weapon",
    "type": "Barrel",
    "damageChange": -1,
    "fireRateChange": 1,
    "rangeChange": 1,
    "removedQualities": ["Close Quarters"],
    "weightChange": 1,
    "costChange": 24,
    "perks": ["Science! 1"]
  },
  {
    "name": "Bracketed Long Barrel",
    "prefix": "",
    "weaponType": "Energy Weapon",
    "type": "Barrel",
    "rangeChange": 1,
    "removedQualities": ["Close Quarters"],
    "effects":"Allows the weapon to take a Muzzle mod",
    "weightChange": 2,
    "costChange": 25,
    "perks": ["Science! 1"]
  },
  {
    "name": "Improved Barrel",
    "prefix": "Improved",
    "weaponType": "Energy Weapon",
    "type": "Barrel",
    "damageChange": 1,
    "weightChange": 1,
    "costChange": 26,
    "perks": ["Science! 1"]
  },
  {
    "name": "Sniper Barrel",
    "prefix": "Sniper",
    "weaponType": "Energy Weapon",
    "type": "Barrel",
    "damageChange": 2,
    "rangeChange": 1,
    "fireRateChange": -1,
    "removedQualities": ["Close Quarters"],
    "weightChange": 2,
    "costChange": 30,
    "perks": ["Science! 1"]
  },
  {
    "name": "Flamer Barrel",
    "prefix": "Thrower",
    "weaponType": "Energy Weapon",
    "type": "Barrel",
    "damageChange": -2,
    "fireRateChange": 2,
    "rangeChange": 1,
    "gainedEffects": ["Burst", "Spread"],
    "gainedQualities": ["Inaccurate"],
    "weightChange": 1,
    "costChange": 35,
    "perks": ["Science! 2"]
  },
  {
    "name": "Sharpshooter’s Grip",
    "prefix": "Sharpshooter’s",
    "weaponType": "Energy Weapon",
    "type": "Grip",
    "gainedEffects": ["Piercing 1"],
    "removedQualities": ["Inaccurate"],
    "weightChange": 0,
    "costChange": 10,
    "perks": ["Gun Nut 1"]
  },
  {
    "name": "Standard Stock",
    "prefix": "",
    "weaponType": "Energy Weapon",
    "type": "Stock",
    "gainedQualities": ["Two-Handed"],
    "removedQualities": ["Inaccurate", "Close Quarters"],
    "weightChange": 1,
    "costChange": 10,
    "perks": []
  },
  {
    "name": "Full Stock",
    "prefix": "",
    "weaponType": "Energy Weapon",
    "type": "Stock",
    "gainedEffects": ["Piercing 1"],
    "removedQualities": ["Close Quarters"],
    "weightChange": 1,
    "costChange": 15,
    "perks": []
  },
  {
    "name": "Marksman’s Stock",
    "prefix": "Marksman’s",
    "weaponType": "Energy Weapon",
    "type": "Stock",
    "gainedQualities": ["Two-Handed", "Accurate"],
    "removedQualities": ["Inaccurate", "Close Quarters"],
    "weightChange": 2,
    "costChange": 20,
    "perks": ["Gun Nut 2"]
  },
  {
    "name": "Recoil Compensating Stock",
    "prefix": "Recoil Compensated",
    "weaponType": "Energy Weapon",
    "type": "Stock",
    "fireRateChange": 1,
    "gainedQualities": ["Two-Handed"],
    "removedQualities": ["Inaccurate", "Close Quarters"],
    "weightChange": 2,
    "costChange": 3,
    "perks": ["Gun Nut 3"]
  },
  {
    "name": "Long Night Vision Scope",
    "prefix": "Night Vision",
    "weaponType": "Energy Weapon",
    "type": "Stock",
    "rangeChange": 1,
    "gainedQualities": ["Accurate", "Night Vision"],
    "weightChange": 1,
    "costChange": 50,
    "perks": ["Science! 3"]
  },
  {
    "name": "Recon Scope",
    "prefix": "Recon",
    "weaponType": "Energy Weapon",
    "type": "Stock",
    "gainedQualities": ["Accurate", "Recon"],
    "weightChange": 1,
    "costChange": 59,
    "perks": ["Science! 3"]
  },
  {
    "name": "Reflex Sight",
    "prefix": "Tactical",
    "weaponType": "Energy Weapon",
    "type": "Sight",
    "effects": "May re-roll hit location die",
    "weightChange": 0,
    "costChange": 14,
    "perks": []
  },
  {
    "name": "Short Scope",
    "prefix": "Scoped",
    "weaponType": "Energy Weapon",
    "type": "Sight",
    "gainedQualities": ["Accurate"],
    "weightChange": 1,
    "costChange": 11,
    "perks": []
  },
  {
    "name": "Long Scope",
    "prefix": "Scoped",
    "weaponType": "Energy Weapon",
    "type": "Sight",
    "rangeChange": 1,
    "gainedQualities": ["Accurate"],
    "weightChange": 1,
    "costChange": 29,
    "perks": ["Science! 2"]
  },
  {
    "name": "Short Night Vision Scope",
    "prefix": "Night Vision",
    "weaponType": "Energy Weapon",
    "type": "Sight",
    "gainedQualities": ["Accurate", "Night Vision"],
    "weightChange": 1,
    "costChange": 38,
    "perks": ["Science! 2"]
  },
  {
    "name": "Long Night Vision Scope",
    "prefix": "Night Vision",
    "weaponType": "Energy Weapon",
    "type": "Sight",
    "rangeChange": 1,
    "gainedQualities": ["Accurate", "Night Vision"],
    "weightChange": 1,
    "costChange": 50,
    "perks": ["Science! 3"]
  },
  {
    "name": "Recon Scope",
    "prefix": "Recon",
    "weaponType": "Energy Weapon",
    "type": "Sight",
    "gainedQualities": ["Accurate", "Recon"],
    "weightChange": 1,
    "costChange": 59,
    "perks": ["Science! 3"]
  },
  {
    "name": "Deep Dish (Gamma Gun)",
    "prefix": "Long",
    "weaponType": "Energy Weapon",
    "type": "Dish",
    "damageChange": 1,
    "rangeChange": 1,
    "weightChange": 2,
    "costChange": 72,
    "perks": ["Science! 4"]
  },
  {
    "name": "Electric Signal Carrier Antennae (Gamma Gun)",
    "prefix": "Electrified",
    "weaponType": "Energy Weapon",
    "type": "Muzzle",
    "fixDamage": 7,
    "newDamageType": "Energy",
    "gainedEffects": ["Radioactive"],
    "weightChange": 0,
    "costChange": 30,
    "perks": ["Science! 3"]
  },
  {
    "name": "Signal Repeater (Gamma Gun)",
    "prefix": "Automatic",
    "weaponType": "Energy Weapon",
    "type": "Muzzle",
    "fireRateChange": 2,
    "gainedEffects": ["Burst"],
    "removedQualities": ["Blast"],
    "weightChange": 0,
    "costChange": 60,
    "perks": ["Science! 4"]
  },
  {
    "name": "Beam Splitter",
    "prefix": "Scattered",
    "weaponType": "Energy Weapon",
    "type": "Muzzle",
    "damageChange": -1,
    "fireRateChange": -1,
    "rangeChange": -1,
    "gainedEffects": ["Spread"],
    "gainedQualities": ["Inaccurate"],
    "weightChange": 1,
    "costChange": 15,
    "perks": ["Science! 1"]
  },
  {
    "name": "Beam Focuser",
    "prefix": "Focused",
    "weaponType": "Energy Weapon",
    "type": "Muzzle",
    "rangeChange": 1,
    "weightChange": 1,
    "costChange": 20,
    "perks": ["Science! 1"]
  },
  {
    "name": "Gyro Compensating Lens",
    "prefix": "Targeting",
    "weaponType": "Energy Weapon",
    "type": "Muzzle",
    "fireRateChange": 1,
    "removedQualities": ["Inaccurate"],
    "weightChange": 1,
    "costChange": 25,
    "perks": ["Science! 1"]
  },
  {
    "name": "Napalm (Flamer)",
    "prefix": "Napalmer",
    "weaponType": "Big Guns",
    "type": "Fuel",
    "damageChange": 1,
    "weightChange": 7,
    "costChange": 59,
    "perks": []
  },
  {
    "name": "Long Barrel (Flamer)",
    "prefix": "Long",
    "weaponType": "Big Guns",
    "type": "Barrel",
    "removedQualities": ["Inaccurate"],
    "weightChange": 2,
    "costChange": 28,
    "perks": []
  },
  {
    "name": "Large Tank (Flamer)",
    "prefix": "High Capacity",
    "weaponType": "Big Guns",
    "type": "Propellant Tank",
    "fireRateChange": 1,
    "weightChange": 3,
    "costChange": 28,
    "perks": []
  },
  {
    "name": "Huge Tank (Flamer)",
    "prefix": "Max. Capacity",
    "weaponType": "Big Guns",
    "type": "Propellant Tank",
    "fireRateChange": 2,
    "weightChange": 6,
    "costChange": 34,
    "perks": []
  },
  {
    "name": "Compression Nozzle (Flamer)",
    "prefix": "Compressed",
    "weaponType": "Big Guns",
    "type": "Nozzle",
    "damageChange": 1,
    "weightChange": 0,
    "costChange": 22,
    "perks": []
  },
  {
    "name": "Vaporization Nozzle (Flamer)",
    "prefix": "Vaporizing",
    "weaponType": "Big Guns",
    "type": "Nozzle",
    "damageChange": 1,
    "gainedEffects": ["Vicious"],
    "weightChange": 0,
    "costChange": 47,
    "perks": []
  },
  {
    "name": "Photon Exciter (Gatling Laser)",
    "prefix": "Excited",
    "weaponType": "Big Guns",
    "type": "Capacitor",
    "gainedEffects": ["Vicious"],
    "weightChange": 1,
    "costChange": 19,
    "perks": ["Science! 3"]
  },
  {
    "name": "Beta Wave Tuner (Gatling Laser)",
    "prefix": "Incendiary",
    "weaponType": "Big Guns",
    "type": "Capacitor",
    "gainedEffects": ["Persistent"],
    "weightChange": 1,
    "costChange": 57,
    "perks": []
  },
  {
    "name": "Boosted Capacitor (Gatling Laser)",
    "prefix": "Boosted",
    "weaponType": "Big Guns",
    "type": "Capacitor",
    "damageChange": 1,
    "weightChange": 1,
    "costChange": 94,
    "perks": []
  },
  {
    "name": "Photon Agitator (Gatling Laser)",
    "prefix": "Agitated",
    "weaponType": "Big Guns",
    "type": "Capacitor",
    "damageChange": 1,
    "gainedEffects": ["Vicious"],
    "weightChange": 3,
    "costChange": 132,
    "perks": ["Science! 3"]
  },
  {
    "name": "Charging barrels (Gatling Laser)",
    "prefix": "Charging",
    "weaponType": "Big Guns",
    "type": "Barrel",
    "damageChange": 4,
    "fireRateChange": -3,
    "rangeChange": 1,
    "weightChange": 10,
    "costChange": 357,
    "perks": ["Science! 4"]
  },
  {
    "name": "Reflex Sight (Gatling Laser)",
    "prefix": "Tactical",
    "weaponType": "Big Guns",
    "type": "Sight",
    "removedQualities": ["Inaccurate"],
    "weightChange": 1,
    "costChange": 169,
    "perks": ["Science! 4"]
  },
  {
    "name": "Beam Focuser (Gatling Laser)",
    "prefix": "Focused",
    "weaponType": "Big Guns",
    "type": "Nozzle",
    "rangeChange": 1,
    "gainedEffects": ["Piercing 1"],
    "weightChange": 0,
    "costChange": 22,
    "perks": []
  },
  {
    "name": "Long Barrel (Junk Jet)",
    "prefix": "Long",
    "weaponType": "Big Guns",
    "type": "Barrel",
    "rangeChange": 1,
    "weightChange": 2,
    "costChange": 20,
    "perks": ["Gun Nut 1"]
  },
  {
    "name": "Recoil Compensating Stock (Junk Jet)",
    "prefix": "Recoil Compensated",
    "weaponType": "Big Guns",
    "type": "Stock",
    "fireRateChange": 1,
    "weightChange": 2,
    "costChange": 40,
    "perks": []
  },
  {
    "name": "Gunner Sight (Junk Jet)",
    "prefix": "Tactical",
    "weaponType": "Big Guns",
    "type": "Sight",
    "effects":"May re-roll hit location die",
    "weightChange": 1,
    "costChange": 5,
    "perks": []
  },
  {
    "name": "Electrification Module (Junk Jet)",
    "prefix": "Electrified",
    "weaponType": "Big Guns",
    "type": "Muzzle",
    "newDamageType": "Energy",
    "gainedEffects": ["Vicious"],
    "weightChange": 1,
    "costChange": 70,
    "perks": ["Gun Nut 2", "Science! 1"]
  },
  {
    "name": "Ignition Module (Junk Jet)",
    "prefix": "Flaming",
    "weaponType": "Big Guns",
    "type": "Muzzle",
    "gainedEffects": ["Persistent (Energy)"],
    "weightChange": 1,
    "costChange": 130,
    "perks": ["Gun Nut 3", "Science! 1"]
  },
  {
    "name": "Accelerated Barrel (Minigun)",
    "prefix": "High-Speed",
    "weaponType": "Big Guns",
    "type": "Barrel",
    "damageChange": 1,
    "fireRateChange": 1,
    "rangeChange": -1,
    "weightChange": 5,
    "costChange": 45,
    "perks": ["Gun Nut 3"]
  },
  {
    "name": "Tri-Barrel (Minigun)",
    "prefix": "High-Powered",
    "weaponType": "Big Guns",
    "type": "Barrel",
    "damageChange": 2,
    "fireRateChange": -2,
    "weightChange": 3,
    "costChange": 75,
    "perks": ["Gun Nut 4"]
  },
  {
    "name": "Gunner Sight (Minigun)",
    "prefix": "Tactical",
    "weaponType": "Big Guns",
    "type": "Sight",
    "removedQualities": ["Inaccurate"],
    "weightChange": 1,
    "costChange": 68,
    "perks": []
  },
  {
    "name": "Shredder (Minigun)",
    "prefix": "Bayoneted Shredding",
    "weaponType": "Big Guns",
    "type": "Muzzle",
    "effects":"As a Melee weapon, deals Physical damage equal to Fire Rate (CD)",
    "weightChange": 5,
    "costChange": 5,
    "perks": ["Gun Nut 2"]
  },
  {
    "name": "Triple Barrel (Missile Launcher)",
    "prefix": "Triple Barrel",
    "weaponType": "Big Guns",
    "type": "Barrel",
    "fireRateChange": 1,
    "weightChange": 16,
    "costChange": 143,
    "perks": ["Gun Nut 2"]
  },
  {
    "name": "Quad Barrel (Missile Launcher)",
    "prefix": "Quad Barrel",
    "weaponType": "Big Guns",
    "type": "Barrel",
    "fireRateChange": 2,
    "weightChange": 20,
    "costChange": 218,
    "perks": ["Gun Nut 3"]
  },
  {
    "name": "Scope (Missile Launcher)",
    "prefix": "Scoped",
    "weaponType": "Big Guns",
    "type": "Sight",
    "gainedQualities": ["Accurate"],
    "weightChange": 6,
    "costChange": 143,
    "perks": ["Gun Nut 2"]
  },
  {
    "name": "Night Vision Scope (Missile Launcher)",
    "prefix": "Night-Vision",
    "weaponType": "Big Guns",
    "type": "Sight",
    "gainedQualities": ["Accurate", "Night Vision"],
    "weightChange": 6,
    "costChange": 248,
    "perks": ["Gun Nut 4", "Science! 1"]
  },
  {
    "name": "Targeting Computer (Missile Launcher)",
    "prefix": "Targeting",
    "weaponType": "Big Guns",
    "type": "Sight",
    "effects": "When you Aim at a target, the target does not benefit from being in cover, and the bonus for aiming applies to the next attack on any subsequent turn during the scene",
    "weightChange": 7,
    "costChange": 293,
    "perks": ["Gun Nut 2", "Science! 2"]
  },
  {
    "name": "Bayonet (Missile Launcher)",
    "prefix": "Bayoneted Shredding",
    "weaponType": "Big Guns",
    "type": "Muzzle",
    "effects":"As a Melee weapon, deals 4CD Piercing 1 Physical damage",
    "weightChange": 1,
    "costChange": 30,
    "perks": []
  },
  {
    "name": "Stabilizer (Missile Launcher)",
    "prefix": "Muzzled",
    "weaponType": "Big Guns",
    "type": "Muzzle",
    "gainedEffects": ["Piercing 1"],
    "weightChange": 2,
    "costChange": 60,
    "perks": ["Gun Nut 2"]
  },
  {
    "name": "Serrated Blade (Sword)",
    "prefix": "Serrated",
    "weaponType": "Melee Weapon",
    "type": "",
    "gainedEffects": ["Persistent"],
    "weightChange": 0,
    "costChange": 25,
    "perks": ["Blacksmith 2"]
  },
  {
    "name": "Electrified Blade (Sword)",
    "prefix": "Electrified",
    "weaponType": "Melee Weapon",
    "type": "",
    "damageChange": 1,
    "newDamageType": "Energy",
    "weightChange": 0,
    "costChange": 50,
    "perks": ["Blacksmith 2", "Science! 1"]
  },
  {
    "name": "Electrified Serrated Blade (Sword)",
    "prefix": "Electrified Serrated",
    "weaponType": "Melee Weapon",
    "type": "",
    "damageChange": 1,
    "newDamageType": "Energy",
    "gainedEffects": ["Persistent (Physical)"],
    "weightChange": 0,
    "costChange": 75,
    "perks": ["Blacksmith 3", "Science! 1"]
  },
  {
    "name": "Stun Pack (Sword)",
    "prefix": "Stunning",
    "weaponType": "Melee Weapon",
    "type": "",
    "damageChange": 2,
    "newDamageType": "Energy",
    "gainedEffects": ["Stun"],
    "weightChange": 0,
    "costChange": 100,
    "perks": ["Blacksmith 3", "Science! 1"]
  },
  {
    "name": "Serrated Blade (Combat Knife)",
    "prefix": "Serrated",
    "weaponType": "Melee Weapon",
    "type": "",
    "damageChange": 1,
    "gainedEffects": ["Persistent"],
    "weightChange": 0,
    "costChange": 12,
    "perks": ["Blacksmith 1"]
  },
  {
    "name": "Stealth Blade (Combat Knife)",
    "prefix": "Stealth",
    "weaponType": "Melee Weapon",
    "type": "",
    "damageChange": 1,
    "gainedEffects": ["Persistent"],
    "effects": "+2 DC on Sneak Attacks",
    "weightChange": 0,
    "costChange": 18,
    "perks": ["Blacksmith 2"]
  },
  {
    "name": "Serrated Blade (Machete)",
    "prefix": "Serrated",
    "weaponType": "Melee Weapon",
    "type": "",
    "damageChange": 2,
    "gainedEffects": ["Persistent"],
    "weightChange": 0,
    "costChange": 12,
    "perks": ["Blacksmith 2"]
  },
  {
    "name": "Curved Blade (Ripper)",
    "prefix": "Curved",
    "weaponType": "Melee Weapon",
    "type": "",
    "damageChange": 1,
    "effects": "On successful attack, spend 2 AP to disarm opponent, knocking one held weapon away",
    "weightChange": 1,
    "costChange": 15,
    "perks": []
  },
  {
    "name": "Extended Blade (Ripper)",
    "prefix": "Extended",
    "weaponType": "Melee Weapon",
    "type": "",
    "damageChange": 1,
    "gainedEffects": ["Persistent"],
    "weightChange": 3,
    "costChange": 25,
    "perks": ["Blacksmith 3"]
  },
  {
    "name": "Extra Flame Jets (Shishkebab)",
    "prefix": "MuzzSearingled",
    "weaponType": "Melee Weapon",
    "type": "",
    "damageChange": 1,
    "gainedEffects": ["Persistent"],
    "weightChange": 1,
    "costChange": 100,
    "perks": ["Blacksmith 3"]
  },
  {
    "name": "Serrated Blade (Switchblade)",
    "prefix": "Serrated",
    "weaponType": "Melee Weapon",
    "type": "",
    "damageChange": 1,
    "gainedEffects": ["Persistent"],
    "weightChange": 0,
    "costChange": 10,
    "perks": ["Blacksmith 1"]
  },
  {
    "name": "Barbed (Baseball Bat)",
    "prefix": "Barbed",
    "weaponType": "Melee Weapon",
    "type": "",
    "gainedEffects": ["Piercing 1"],
    "weightChange": 0,
    "costChange": 5,
    "perks": []
  },
  {
    "name": "Spiked (Baseball Bat)",
    "prefix": "Spiked",
    "weaponType": "Melee Weapon",
    "type": "",
    "damageChange": 1,
    "gainedEffects": ["Piercing 1"],
    "weightChange": 1,
    "costChange": 7,
    "perks": []
  },
  {
    "name": "Sharp (Baseball Bat)",
    "prefix": "Sharp",
    "weaponType": "Melee Weapon",
    "type": "",
    "damageChange": 1,
    "gainedEffects": ["Persistent"],
    "weightChange": 1,
    "costChange": 7,
    "perks": []
  },
  {
    "name": "Chain-Wrapped (Baseball Bat)",
    "prefix": "Chain-Wrapped",
    "weaponType": "Melee Weapon",
    "type": "",
    "damageChange": 2,
    "weightChange": 1,
    "costChange": 10,
    "perks": ["Blacksmith 1"]
  },
  {
    "name": "Bladed (Baseball Bat)",
    "prefix": "Bladed",
    "weaponType": "Melee Weapon",
    "type": "",
    "damageChange": 2,
    "gainedEffects": ["Persistent"],
    "weightChange": 2,
    "costChange": 12,
    "perks": ["Blacksmith 2"]
  },
  {
    "name": "Spiked (Board)",
    "prefix": "Spiked",
    "weaponType": "Melee Weapon",
    "type": "",
    "damageChange": 1,
    "gainedEffects": ["Piercing 1"],
    "weightChange": 1,
    "costChange": 6,
    "perks": []
  },
  {
    "name": "Puncturing (Board)",
    "prefix": "Puncturing",
    "weaponType": "Melee Weapon",
    "type": "",
    "damageChange": 2,
    "weightChange": 1,
    "costChange": 9,
    "perks": ["Blacksmith 1"]
  },
  {
    "name": "Bladed (Board)",
    "prefix": "Bladed",
    "weaponType": "Melee Weapon",
    "type": "",
    "damageChange": 2,
    "gainedEffects": ["Persistent"],
    "weightChange": 2,
    "costChange": 10,
    "perks": ["Blacksmith 1"]
  },
  {
    "name": "Spiked (Lead Pipe)",
    "prefix": "Spiked",
    "weaponType": "Melee Weapon",
    "type": "",
    "damageChange": 1,
    "gainedEffects": ["Piercing 1"],
    "weightChange": 1,
    "costChange": 4,
    "perks": []
  },
  {
    "name": "Heavy (Lead Pipe)",
    "prefix": "Heavy",
    "weaponType": "Melee Weapon",
    "type": "",
    "damageChange": 2,
    "weightChange": 2,
    "costChange": 11,
    "perks": ["Blacksmith 2"]
  },
  {
    "name": "Hooked (Pipe Wrench)",
    "prefix": "Hooked",
    "weaponType": "Melee Weapon",
    "type": "",
    "damageChange": 1,
    "effects": "On successful attack, spend 2 AP to disarm opponent, knocking one held weapon away",
    "weightChange": 0,
    "costChange": 9,
    "perks": []
  },
  {
    "name": "Heavy (Pipe Wrench)",
    "prefix": "Weighted",
    "weaponType": "Melee Weapon",
    "type": "",
    "damageChange": 2,
    "weightChange": 7,
    "costChange": 12,
    "perks": ["Blacksmith 1"]
  },
  {
    "name": "Puncturing (Pipe Wrench)",
    "prefix": "Puncturing",
    "weaponType": "Melee Weapon",
    "type": "",
    "damageChange": 2,
    "gainedEffects": ["Piercing 1"],
    "weightChange": 1,
    "costChange": 13,
    "perks": ["Blacksmith 1"]
  },
  {
    "name": "Extra Heavy (Pipe Wrench)",
    "prefix": "Heavy",
    "weaponType": "Melee Weapon",
    "type": "",
    "damageChange": 3,
    "weightChange": 2,
    "costChange": 22,
    "perks": ["Blacksmith 2"]
  },
  {
    "name": "Barbed (Pool Cue)",
    "prefix": "Barbed",
    "weaponType": "Melee Weapon",
    "type": "",
    "damageChange": 1,
    "gainedEffects": ["Piercing 1"],
    "weightChange": 0,
    "costChange": 2,
    "perks": []
  },
  {
    "name": "Sharp (Pool Cue)",
    "prefix": "Sharp",
    "weaponType": "Melee Weapon",
    "type": "",
    "damageChange": 1,
    "gainedEffects": ["Persistent"],
    "weightChange": 0,
    "costChange": 3,
    "perks": []
  },
  {
    "name": "Spiked (Rolling Pin)",
    "prefix": "Barbed",
    "weaponType": "Melee Weapon",
    "type": "",
    "damageChange": 1,
    "gainedEffects": ["Piercing 1"],
    "weightChange": 0,
    "costChange": 3,
    "perks": []
  },
  {
    "name": "Sharp (Rolling Pin)",
    "prefix": "Sharp",
    "weaponType": "Melee Weapon",
    "type": "",
    "damageChange": 1,
    "gainedEffects": ["Persistent"],
    "weightChange": 0,
    "costChange": 3,
    "perks": []
  },
  {
    "name": "Electrified (Baton)",
    "prefix": "Shock",
    "weaponType": "Melee Weapon",
    "type": "",
    "damageChange": 2,
    "newDamageType": "Energy",
    "weightChange": 0,
    "costChange": 15,
    "perks": ["Blacksmith 2", "Science! 1"]
  },
  {
    "name": "Stun Pack (Baton)",
    "prefix": "Stun",
    "weaponType": "Melee Weapon",
    "type": "",
    "damageChange": 3,
    "newDamageType": "Energy",
    "gainedEffects": ["Stun"],
    "weightChange": 0,
    "costChange": 30,
    "perks": ["Blacksmith 2", "Science! 1"]
  },
  {
    "name": "Puncturing (Sledgehammer)",
    "prefix": "Puncturing",
    "weaponType": "Melee Weapon",
    "type": "",
    "damageChange": 1,
    "gainedEffects": ["Piercing 1"],
    "weightChange": 5,
    "costChange": 18,
    "perks": ["Blacksmith 2"]
  },
  {
    "name": "Heavy (Sledgehammer)",
    "prefix": "Heavy",
    "weaponType": "Melee Weapon",
    "type": "",
    "damageChange": 2,
    "weightChange": 9,
    "costChange": 30,
    "perks": ["Blacksmith 2"]
  },
  {
    "name": "Heating Coil (Super Sledge)",
    "prefix": "Heated",
    "weaponType": "Melee Weapon",
    "type": "",
    "damageChange": 1,
    "newDamageType": "Energy",
    "weightChange": 0,
    "costChange": 180,
    "perks": ["Blacksmith 2"]
  },
  {
    "name": "Stun Pack (Super Sledge)",
    "prefix": "Stunning",
    "weaponType": "Melee Weapon",
    "type": "",
    "damageChange": 2,
    "newDamageType": "Energy",
    "gainedEffects": ["Stun"],
    "weightChange": 0,
    "costChange": 360,
    "perks": ["Blacksmith 3", "Science! 1"]
  },
  {
    "name": "Bladed (Tire Iron)",
    "prefix": "Bladed",
    "weaponType": "Melee Weapon",
    "type": "",
    "damageChange": 1,
    "gainedEffects": ["Persistent"],
    "weightChange": 1,
    "costChange": 12,
    "perks": ["Blacksmith 2"]
  },
  {
    "name": "Barbed (Walking Cane)",
    "prefix": "Barbed",
    "weaponType": "Melee Weapon",
    "type": "",
    "damageChange": 1,
    "gainedEffects": ["Piercing 1"],
    "weightChange": 0,
    "costChange": 3,
    "perks": []
  },
  {
    "name": "Spiked (Walking Cane)",
    "prefix": "Spiked",
    "weaponType": "Melee Weapon",
    "type": "",
    "damageChange": 1,
    "gainedEffects": ["Piercing 1"],
    "weightChange": 0,
    "costChange": 3,
    "perks": []
  },
  {
    "name": "Spiked (Boxing Glove)",
    "prefix": "Spiked",
    "weaponType": "Melee Weapon",
    "type": "",
    "gainedEffects": ["Piercing 1"],
    "weightChange": 0,
    "costChange": 3,
    "perks": []
  },
  {
    "name": "Puncturing (Boxing Glove)",
    "prefix": "Puncturing",
    "weaponType": "Melee Weapon",
    "type": "",
    "damageChange": 1,
    "gainedEffects": ["Piercing 1"],
    "weightChange": 0,
    "costChange": 4,
    "perks": ["Blacksmith 1"]
  },
  {
    "name": "Lead lining (Boxing Glove)",
    "prefix": "Lead-lined",
    "weaponType": "Melee Weapon",
    "type": "",
    "damageChange": 2,
    "weightChange": 1,
    "costChange": 7,
    "perks": ["Blacksmith 1"]
  },
  {
    "name": "Extra Claw (Deathclaw Gauntlet)",
    "prefix": "Large",
    "weaponType": "Melee Weapon",
    "type": "",
    "damageChange": 1,
    "effects": "On successful attack, spend 2 AP to disarm opponent, knocking one held weapon away",
    "weightChange": 2,
    "costChange": 22,
    "perks": []
  },
  {
    "name": "Sharp (Knuckles)",
    "prefix": "Sharp",
    "weaponType": "Melee Weapon",
    "type": "",
    "gainedEffects": ["Persistent"],
    "weightChange": 0,
    "costChange": 3,
    "perks": []
  },
  {
    "name": "Spiked (Knuckles)",
    "prefix": "Spiked",
    "weaponType": "Melee Weapon",
    "type": "",
    "gainedEffects": ["Piercing 1"],
    "weightChange": 0,
    "costChange": 3,
    "perks": []
  },
  {
    "name": "Puncturing (Knuckles)",
    "prefix": "Puncturing",
    "weaponType": "Melee Weapon",
    "type": "",
    "damageChange": 1,
    "gainedEffects": ["Piercing 1"],
    "weightChange": 0,
    "costChange": 4,
    "perks": ["Blacksmith 1"]
  },
  {
    "name": "Bladed (Knuckles)",
    "prefix": "Bladed",
    "weaponType": "Melee Weapon",
    "type": "",
    "damageChange": 1,
    "gainedEffects": ["Persistent"],
    "weightChange": 0,
    "costChange": 5,
    "perks": ["Blacksmith 1"]
  },
  {
    "name": "Puncturing (Power Fist)",
    "prefix": "Puncturing",
    "weaponType": "Melee Weapon",
    "type": "",
    "damageChange": 2,
    "gainedEffects": ["Piercing 1"],
    "weightChange": 1,
    "costChange": 45,
    "perks": ["Blacksmith 2"]
  },
  {
    "name": "Heating Coil (Power Fist)",
    "prefix": "Heated",
    "weaponType": "Melee Weapon",
    "type": "",
    "damageChange": 2,
    "newDamageType": "Energy",
    "weightChange": 0,
    "costChange": 100,
    "perks": ["Blacksmith 3"]
  },
  {
    "name": "Long Barrel (M79 Grenade Launcher)",
    "prefix": "Long",
    "weaponType": "Small Guns",
    "type": "Barrel",
    "rangeChange": 1,
    "weightChange": 2,
    "costChange": 40,
    "perks": ["Gun Nut 1"]
  },
  {
    "name": "Full Stock (M79 Grenade Launcher)",
    "prefix": "",
    "weaponType": "Small Guns",
    "type": "Stock",
    "gainedQualities": ["Two-Handed"],
    "removedQualities": ["Inaccurate"],
    "weightChange": 1,
    "costChange": 10,
    "perks": []
  },
  {
    "name": "Caustic (Acid Soaker)",
    "prefix": "Caustic",
    "weaponType": "Energy Weapon",
    "type": "Concentrate",
    "damageChange": 1,
    "weightChange": 2,
    "costChange": 30,
    "perks": []
  },
  {
    "name": "Large Ampoule (Acid Soaker)",
    "prefix": "High Capacity",
    "weaponType": "Energy Weapon",
    "type": "Container",
    "fireRateChange": 1,
    "weightChange": 2,
    "costChange": 22,
    "perks": []
  },
  {
    "name": "Large Vial (Acid Soaker)",
    "prefix": "Maximum Capacity",
    "weaponType": "Energy Weapon",
    "type": "Container",
    "fireRateChange": 3,
    "weightChange": 4,
    "costChange": 40,
    "perks": []
  },
  {
    "name": "Fusion Mag (Alien Blaster)",
    "prefix": "Converted",
    "weaponType": "Energy Weapon",
    "type": "Magazine",
    "fixDamage": 3,
    "fireRateChange": -1,
    "ammo": "Fusion Cell",
    "weightChange": 0,
    "costChange": 21,
    "perks": ["Science! 1"]
  },
  {
    "name": "Capacitor Mk III (Assaultron Head)",
    "prefix": "Mk III",
    "weaponType": "Energy Weapon",
    "type": "Capacitor",
    "damageChange": 1,
    "effects": "consumes 3 shots per attack",
    "weightChange": 0,
    "costChange": 4,
    "perks": ["Robotics Expert"]
  },
  {
    "name": "Capacitor Mk IV (Assaultron Head)",
    "prefix": "Mk IV",
    "weaponType": "Energy Weapon",
    "type": "Capacitor",
    "damageChange": 2,
    "effects": "consumes 4 shots per attack",
    "weightChange": 1,
    "costChange": 8,
    "perks": ["Robotics Expert", "Science! 1"]
  },
  {
    "name": "Capacitor Mk V (Assaultron Head)",
    "prefix": "Mk V",
    "weaponType": "Energy Weapon",
    "type": "Capacitor",
    "damageChange": 3,
    "effects": "consumes 5 shots per attack",
    "weightChange": 1,
    "costChange": 12,
    "perks": ["Robotics Expert", "Science! 2"]
  },
  {
    "name": "Capacitor Mk VI (Assaultron Head)",
    "prefix": "Mk VI",
    "weaponType": "Energy Weapon",
    "type": "Capacitor",
    "damageChange": 4,
    "effects": "consumes 6 shots per attack",
    "weightChange": 2,
    "costChange": 16,
    "perks": ["Robotics Expert", "Science! 3"]
  },
  {
    "name": "Long Barrel (Broadsider)",
    "prefix": "Long",
    "weaponType": "Big Guns",
    "type": "Barrel",
    "rangeChange": 1,
    "weightChange": 2,
    "costChange": 40,
    "perks": ["Gun Nut 1"]
  },
  {
    "name": "Light Barrel (Broadsider)",
    "prefix": "Fluted",
    "weaponType": "Big Guns",
    "type": "Barrel",
    "damageChange": 2,
    "removedQualities": ["Blast"],
    "weightChange": 3,
    "costChange": 30,
    "perks": ["Gun Nut 2"]
  },
  {
    "name": "Multi Shot Canister (Broadsider)",
    "prefix": "Repeating",
    "weaponType": "Big Guns",
    "type": "Cannister",
    "fireRateChange": 1,
    "gainedQualities": ["Inaccurate"],
    "weightChange": 1,
    "costChange": 45,
    "perks": ["Gun Nut 3"]
  },
  {
    "name": "M79 Launcher (Broadsider)",
    "prefix": "Converted",
    "weaponType": "Big Guns",
    "type": "Cannister",
    "rangeChange": 1,
    "ammo": "40mm grenade round",
    "weightChange": 0,
    "costChange": 3,
    "perks": ["Science! 1"]
  },
  {
    "name": "Crystallizing Barrel (Cryolator)",
    "prefix": "Crystallized",
    "weaponType": "Big Guns",
    "type": "Barrel",
    "damageChange": 2,
    "rangeChange": 1,
    "fireRateChange": -1,
    "removedEffect": ["Stun"],
    "removedQualities": ["Unreliable"],
    "weightChange": 5,
    "costChange": 40,
    "perks": ["Science! 2"]
  },
  {
    "name": "Fusion Mag (Cryolator)",
    "prefix": "Converted",
    "weaponType": "Big Guns",
    "type": "Magazine",
    "fixDamage": 2,
    "fireRateChange": -1,
    "ammo": "Fusion Cell",
    "weightChange": 0,
    "costChange": 21,
    "perks": ["Science! 1"]
  },
  {
    "name": "Recoil Compensating Stock (Cryolator)",
    "prefix": "Recoil Compensating",
    "weaponType": "Big Guns",
    "type": "Stock",
    "fireRateChange": 1,
    "weightChange": 2,
    "costChange": 45,
    "perks": []
  },
  {
    "name": "Reflex (Cryolator)",
    "prefix": "Tactical",
    "weaponType": "Big Guns",
    "type": "Sight",
    "effects": "May re-roll hit location die",
    "weightChange": 0,
    "costChange": 17,
    "perks": []
  },
  {
    "name": "Barbed Harpoon (Harpoon Gun)",
    "prefix": "Barbed",
    "weaponType": "Big Guns",
    "type": "Magazine",
    "gainedEffects": ["Vicious", "Persistent"],
    "weightChange": 0,
    "costChange": 21,
    "perks": []
  },
  {
    "name": "Flechette Darts (Harpoon Gun)",
    "prefix": "Tiny",
    "weaponType": "Big Guns",
    "type": "Magazine",
    "rangeChange": -1,
    "gainedEffects": ["Spread"],
    "weightChange": 0,
    "costChange": 15,
    "perks": ["Gun Nut 2"]
  },
  {
    "name": "Recoil Compensating Stock (Harpoon Gun)",
    "prefix": "Recoil Compensating",
    "weaponType": "Big Guns",
    "type": "Stock",
    "fireRateChange": 1,
    "weightChange": 15,
    "costChange": 45,
    "perks": []
  },
  {
    "name": "Gunner Sight (Harpoon Gun)",
    "prefix": "Tactical",
    "weaponType": "Big Guns",
    "type": "Sight",
    "effects": "May re-roll hit location die",
    "weightChange": 0,
    "costChange": 17,
    "perks": []
  },
  {
    "name": "Short Scope (Harpoon Gun)",
    "prefix": "Scoped",
    "weaponType": "Big Guns",
    "type": "Sight",
    "gainedQualities": ["Accurate"],
    "weightChange": 1,
    "costChange": 28,
    "perks": ["Gun Nut 1"]
  },
  {
    "name": "Shock Mod (Claw)",
    "prefix": "Shock",
    "weaponType": "Unarmed",
    "type": "",
    "damageChange": 2,
    "newDamageType": "Energy",
    "weightChange": 0,
    "costChange": 15,
    "perks": ["Blacksmith 2", "Robotics Expert"]
  },
  {
    "name": "Stun Mod (Claw)",
    "prefix": "Stun",
    "weaponType": "Unarmed",
    "type": "",
    "damageChange": 3,
    "newDamageType": "Energy",
    "gainedEffects": ["Stun"],
    "weightChange": 0,
    "costChange": 30,
    "perks": ["Blacksmith 2", "Robotics Expert"]
  },
  {
    "name": "Armor Piercing Receiver",
    "prefix": "Armor Piercing",
    "weaponType": "Small Guns",
    "type": "Receiver",
    "gainedEffects": ["Piercing 1"],
    "weightChange": 0,
    "costChange": 3,
    "perks": ["Gun Nut 1"]
  },
  {
    "name": "Armor Piercing Automatic Receiver",
    "prefix": "AP Auto",
    "weaponType": "Small Guns",
    "type": "Receiver",
    "damageChange": -1,
    "fireRateChange": 2,
    "gainedEffects": ["Piercing 1"],
    "gainedQualities": ["Inaccurate"],
    "weightChange": 1,
    "costChange": 40,
    "perks": ["Gun Nut 3"]
  },
  {
    "name": "Hardened Automatic Receiver",
    "prefix": "Hardened Auto",
    "weaponType": "Small Guns",
    "type": "Receiver",
    "fireRateChange": 2,
    "gainedQualities": ["Inaccurate"],
    "weightChange": 2,
    "costChange": 58,
    "perks": ["Gun Nut 3"]
  },
  {
    "name": "Rapid Automatic Receiver",
    "prefix": "Rapid",
    "weaponType": "Small Guns",
    "type": "Receiver",
    "damageChange": -1,
    "fireRateChange": 3,
    "gainedQualities": ["Inaccurate"],
    "weightChange": 2,
    "costChange": 63,
    "perks": ["Gun Nut 4"]
  },
  {
    "name": "Calibrated Powerful Receiver",
    "prefix": "Calibrated Powerful",
    "weaponType": "Small Guns",
    "type": "Receiver",
    "damageChange": 2,
    "gainedEffects": ["Vicious"],
    "weightChange": 3,
    "costChange": 68,
    "perks": ["Gun Nut 4"]
  },
  {
    "name": "Powerful Automatic Receiver",
    "prefix": "Powerful Auto",
    "weaponType": "Small Guns",
    "type": "Receiver",
    "damageChange": 1,
    "fireRateChange": 2,
    "gainedQualities": ["Inaccurate"],
    "weightChange": 4,
    "costChange": 88,
    "perks": ["Gun Nut 4"]
  },
  {
    "name": "Hardened Piercing Auto Receiver",
    "prefix": "Hardened AP Auto",
    "weaponType": "Small Guns",
    "type": "Receiver",
    "fireRateChange": 2,
    "gainedEffects": ["Piercing 1"],
    "gainedQualities": ["Inaccurate"],
    "weightChange": 3,
    "costChange": 78,
    "perks": ["Gun Nut 4"]
  },
  {
    "name": "9mm Receiver",
    "prefix": "9mm",
    "weaponType": "Small Guns",
    "type": "Receiver",
    "fixDamage": 3,
    "ammo": "9mm",
    "fireRateChange": 1,
    "weightChange": -1,
    "costChange": 10,
    "perks": ["Gun Nut 2"]
  },
  {
    "name": ".357 Receiver",
    "prefix": ".357",
    "weaponType": "Small Guns",
    "type": "Receiver",
    "fixDamage": 5,
    "ammo": ".357",
    "gainedEffects": ["Vicious"],
    "weightChange": 1,
    "costChange": 35,
    "perks": ["Gun Nut 3"]
  },
  {
    "name": "Gamma Wave Emitter",
    "prefix": "Fiery",
    "weaponType": "Energy Weapon",
    "type": "Capacitor",
    "damageChange": 1,
    "gainedEffects": ["Persistent"],
    "weightChange": 1,
    "costChange": 14,
    "perks": ["Science! 1"]
  },
  {
    "name": "Maximized Capacitor",
    "prefix": "Maximized",
    "weaponType": "Energy Weapon",
    "type": "Capacitor",
    "damageChange": 2,
    "weightChange": 1,
    "costChange": 17,
    "perks": ["Science! 2"]
  },
  {
    "name": "Boosted Photon Agitator",
    "prefix": "Boosted, Agitated",
    "weaponType": "Energy Weapon",
    "type": "Capacitor",
    "damageChange": 2,
    "gainedEffects": ["Vicious"],
    "weightChange": 1,
    "costChange": 20,
    "perks": ["Science! 2"]
  },
  {
    "name": "Boosted Gamma Wave Emitter",
    "prefix": "Boosted, Fiery",
    "weaponType": "Energy Weapon",
    "type": "Capacitor",
    "damageChange": 2,
    "gainedEffects": ["Persistent"],
    "weightChange": 1,
    "costChange": 23,
    "perks": ["Science! 2"]
  },
  {
    "name": "Overcharged Capacitor",
    "prefix": "Overcharged",
    "weaponType": "Energy Weapon",
    "type": "Capacitor",
    "damageChange": 3,
    "weightChange": 1,
    "costChange": 42,
    "perks": ["Science! 2"]
  },
  {
    "name": "Improved Long Barrel",
    "prefix": "Improved Long",
    "weaponType": "Energy Weapon",
    "type": "Barrel",
    "damageChange": 1,
    "rangeChange": 1,
    "removedQualities": ["Close Quarters"],
    "weightChange": 1,
    "costChange": 15,
    "perks": ["Science! 2"]
  },
  {
    "name": "Improved Automatic Barrel",
    "prefix": "Improved Automatic",
    "weaponType": "Energy Weapon",
    "type": "Barrel",
    "rangeChange": 1,
    "fireRateChange": 1,
    "gainedEffects": ["Burst"],
    "gainedQualities": ["Inaccurate"],
    "removedQualities": ["Close Quarters"],
    "weightChange": 1,
    "costChange": 18,
    "perks": ["Science! 2"]
  },
  {
    "name": "Improved Sniper Barrel",
    "prefix": "Improved Charging",
    "weaponType": "Energy Weapon",
    "type": "Barrel",
    "damageChange": 3,
    "rangeChange": 1,
    "fireRateChange": -1,
    "removedQualities": ["Close Quarters"],
    "weightChange": 1,
    "costChange": 21,
    "perks": ["Science! 2"]
  },
  {
    "name": "Improved Splitter",
    "prefix": "Improved Scattergun",
    "weaponType": "Energy Weapon",
    "type": "Barrel",
    "gainedEffects": ["Spread"],
    "gainedQualities": ["Inaccurate"],
    "weightChange": 1,
    "costChange": 25,
    "perks": ["Science! 2"]
  },
  {
    "name": "Amplified Beam Splitter",
    "prefix": "Improved Scattered",
    "weaponType": "Energy Weapon",
    "type": "Muzzle",
    "fireRateChange": -1,
    "rangeChange": -1,
    "gainedEffects": ["Spread"],
    "weightChange": 1,
    "costChange": 15,
    "perks": ["Science! 2"]
  },
  {
    "name": "Fine-Tuned Beam Focuser",
    "prefix": "Improved Focused",
    "weaponType": "Energy Weapon",
    "type": "Muzzle",
    "rangeChange": 1,
    "gainedQualities": ["Accurate"],
    "weightChange": 1,
    "costChange": 18,
    "perks": ["Science! 2"]
  },
  {
    "name": "Quantum Gyro Compensating Lens",
    "prefix": "Improved Targeting",
    "weaponType": "Energy Weapon",
    "type": "Muzzle",
    "fireRateChange": 2,
    "removedQualities": ["Inaccurate"],
    "weightChange": 1,
    "costChange": 21,
    "perks": ["Science! 3"]
  },
  {
    "name": "Gamma Wave Emitter (Gatling Laser)",
    "prefix": "Fiery",
    "weaponType": "Big Guns",
    "type": "Capacitor",
    "damageChange": 1,
    "gainedEffects": ["Persistent"],
    "weightChange": 3,
    "costChange": 169,
    "perks": ["Science! 3"]
  },
  {
    "name": "Maximized Capacitor (Gatling Laser)",
    "prefix": "Maximized",
    "weaponType": "Big Guns",
    "type": "Capacitor",
    "damageChange": 2,
    "weightChange": 3,
    "costChange": 207,
    "perks": ["Science! 4"]
  },
  {
    "name": "Boosted Photon Agitator (Gatling Laser)",
    "prefix": "Boosted, Agitated",
    "weaponType": "Big Guns",
    "type": "Capacitor",
    "damageChange": 2,
    "gainedEffects": ["Vicious"],
    "weightChange": 5,
    "costChange": 244,
    "perks": ["Science! 4"]
  },
  {
    "name": "Boosted Gamma Wave Emitter (Gatling Laser)",
    "prefix": "Boosted Fiery",
    "weaponType": "Big Guns",
    "type": "Capacitor",
    "damageChange": 2,
    "gainedEffects": ["Persistent"],
    "weightChange": 5,
    "costChange": 282,
    "perks": ["Science! 4"]
  },
  {
    "name": "Overcharged Capacitor (Gatling Laser)",
    "prefix": "Overcharged",
    "weaponType": "Big Guns",
    "type": "Capacitor",
    "damageChange": 3,
    "weightChange": 5,
    "costChange": 319,
    "perks": ["Science! 4"]
  },
  {
    "name": "Heavy Barrel (.50 Cal Machine Gun)",
    "prefix": "",
    "weaponType": "Big Guns",
    "type": "Barrel",
    "damageChange": 1,
    "gainedEffects": ["Vicious"],
    "weightChange": 3,
    "costChange": 35,
    "perks": ["Gun Nut 4"]
  },
  {
    "name": "Heavy Barrel (Auto Grenade Launcher)",
    "prefix": "",
    "weaponType": "Big Guns",
    "type": "Barrel",
    "damageChange": 1,
    "gainedEffects": ["Vicious"],
    "weightChange": 3,
    "costChange": 135,
    "perks": ["Gun Nut 4"]
  },
  {
    "name": "Long Barrel (Auto Grenade Launcher)",
    "prefix": "",
    "weaponType": "Big Guns",
    "type": "Barrel",
    "rangeChange": 1,
    "weightChange": 2,
    "costChange": 45,
    "perks": ["Gun Nut 4"]
  },
  {
    "name": "25mm Grenade Receiver (Auto Grenade Launcher)",
    "prefix": "",
    "weaponType": "Big Guns",
    "type": "Receiver",
    "fixDamage": 4,
    "fireRateChange": 2,
    "ammo": "25mm Grenade",
    "weightChange": -3,
    "costChange": 135,
    "perks": ["Gun Nut 4"]
  },
  {
    "name": "Speedy Receiver (Gatling Gun)",
    "prefix": "",
    "weaponType": "Big Guns",
    "type": "Receiver",
    "fireRateChange": 2,
    "weightChange": 1,
    "costChange": 35,
    "perks": ["Gun Nut 3"]
  },
  {
    "name": "Long Barrel (Gatling Gun)",
    "prefix": "Long",
    "weaponType": "Big Guns",
    "type": "Barrel",
    "rangeChange": 1,
    "weightChange": 2,
    "costChange": 158,
    "perks": ["Gun Nut 4"]
  },
  {
    "name": "Comfort Grip (Gatling Gun)",
    "prefix": "Comfort Grip",
    "weaponType": "Big Guns",
    "type": "Grip",
    "removedQualities": ["Recoil (6)"],
    "weightChange": 3,
    "costChange": 90,
    "perks": ["Gun Nut 4"]
  },
  {
    "name": "Extra-Large Magazine (Gatling Gun)",
    "prefix": "",
    "weaponType": "Big Guns",
    "type": "Magazine",
    "fireRateChange": 1,
    "gainedQualities": ["Unreliable"],
    "weightChange": 2,
    "costChange": 28,
    "perks": ["Gun Nut 4"]
  },
  {
    "name": "Front Sight Ring (Gatling Gun)",
    "prefix": "Sighted",
    "weaponType": "Big Guns",
    "type": "Sight",
    "removedQualities": ["Inaccurate"],
    "weightChange": 2,
    "costChange": 158,
    "perks": ["Gun Nut 4"]
  },
  {
    "name": "Large Bayonet (Gatling Gun)",
    "prefix": "Bayoneted",
    "weaponType": "Big Guns",
    "type": "Muzzle",
    "effects":"As a Melee weapon, deals 5 CD Piercing 1 Physical damage",
    "weightChange": 5,
    "costChange": 18,
    "perks": ["Gun Nut 4"]
  },
  {
    "name": "Ported Barrel (Gatling Plasma)",
    "prefix": "Ported",
    "weaponType": "Big Guns",
    "type": "Barrel",
    "removedQualities": ["Inaccurate"],
    "weightChange": 6,
    "costChange": 81,
    "perks": ["Science! 4"]
  },
  {
    "name": "Comfort Grip (Gatling Plasma)",
    "prefix": "Comfort Grip",
    "weaponType": "Big Guns",
    "type": "Grip",
    "removedQualities": ["Recoil (6)"],
    "weightChange": 3,
    "costChange": 90,
    "perks": ["Science! 4"]
  },
  {
    "name": "Reflex Sight (Gatling Plasma)",
    "prefix": "Sighted",
    "weaponType": "Big Guns",
    "type": "Sight",
    "effects": "May re-roll hit location die",
    "weightChange": 2,
    "costChange": 50,
    "perks": ["Gun Nut 2"]
  },
  {
    "name": "Beam Splitter (Gatling Plasma)",
    "prefix": "Scattered",
    "weaponType": "Big Guns",
    "type": "Nozzle",
    "gainedEffects": ["Spread"],
    "weightChange": 3,
    "costChange": 20,
    "perks": ["Science! 4"]
  },
  {
    "name": "Beam Focuser (Gatling Plasma)",
    "prefix": "Focused",
    "weaponType": "Big Guns",
    "type": "Nozzle",
    "rangeChange": 1,
    "weightChange": 4,
    "costChange": 41,
    "perks": ["Science! 4"]
  },
  {
    "name": "Tri-Barrel (Gauss Minigun)",
    "prefix": "Triple Barrel",
    "weaponType": "Big Guns",
    "type": "Barrel",
    "fireRateChange": 1,
    "weightChange": 4,
    "costChange": 91,
    "perks": ["Science! 1"]
  },
  {
    "name": "Penta-Barrel (Gauss Minigun)",
    "prefix": "Penta Barrel",
    "weaponType": "Big Guns",
    "type": "Barrel",
    "damageChange": -1,
    "rangeChange": 1,
    "fireRateChange": 2,
    "weightChange": 12,
    "costChange": 182,
    "perks": ["Science! 1"]
  },
  {
    "name": "Tesla Coil Capacitor (Gauss Minigun)",
    "prefix": "Tesla Capacitor",
    "weaponType": "Big Guns",
    "type": "Tesla Coil",
    "newDamageType": "Energy",
    "weightChange": 8,
    "costChange": 91,
    "perks": ["Science! 1"]
  },
  {
    "name": "Tesla Coil Dynamo (Gauss Minigun)",
    "prefix": "Tesla Dynamo",
    "weaponType": "Big Guns",
    "type": "Tesla Coil",
    "newDamageType": "Energy",
    "fireRateChange": 1,
    "weightChange": 12,
    "costChange": 136,
    "perks": ["Science! 2"]
  },
  {
    "name": "Gunner Sight (Gauss Minigun)",
    "prefix": "Tactical",
    "weaponType": "Big Guns",
    "type": "Sight",
    "effects": "May re-roll hit location die",
    "weightChange": 1,
    "costChange": 5,
    "perks": []
  },
  {
    "name": "Calibrated Capacitor (Plasma Caster)",
    "prefix": "",
    "weaponType": "Big Guns",
    "type": "Capacitor",
    "gainedEffects": ["Vicious"],
    "weightChange": 3,
    "costChange": 140,
    "perks": ["Science! 4"]
  },
  {
    "name": "Pulse Capacitor (Plasma Caster)",
    "prefix": "Pulse",
    "weaponType": "Big Guns",
    "type": "Capacitor",
    "gainedQualities": ["Surge"],
    "weightChange": 3,
    "costChange": 70,
    "perks": ["Science! 3"]
  },
  {
    "name": "High Speed Electrode (Plasma Caster)",
    "prefix": "Rapid",
    "weaponType": "Big Guns",
    "type": "Capacitor",
    "fireRateChange": 1,
    "weightChange": 3,
    "costChange": 105,
    "perks": ["Science! 3"]
  },
  {
    "name": "Long Barrel (Plasma Caster)",
    "prefix": "",
    "weaponType": "Big Guns",
    "type": "Barrel",
    "rangeChange": 1,
    "weightChange": 5,
    "costChange": 128,
    "perks": ["Science! 4"]
  },
  {
    "name": "Compound Frame (Bow)",
    "prefix": "Compound",
    "weaponType": "Bow",
    "type": "Frame",
    "damageChange": 1,
    "fireRateChange": -1,
    "removedQualities": ["Recoil (6)"],
    "weightChange": 1,
    "costChange": 30,
    "perks": ["Gun Nut 1"]
  },
  {
    "name": "Iron Sights (Bow)",
    "prefix": "",
    "weaponType": "Bow",
    "type": "Sight",
    "rangeChange": 1,
    "weightChange": 1,
    "costChange": 10,
    "perks": ["Gun Nut 1"]
  },
  {
    "name": "Glow Sights (Bow)",
    "prefix": "Glow-Sighted",
    "weaponType": "Bow",
    "type": "Sight",
    "rangeChange": 1,
    "gainedQualities": ["Accurate"],
    "weightChange": 1,
    "costChange": 15,
    "perks": ["Gun Nut 2"]
  },
  {
    "name": "Iron Sights (Crossbow)",
    "prefix": "",
    "weaponType": "Bow",
    "type": "Sight",
    "rangeChange": 1,
    "weightChange": 1,
    "costChange": 10,
    "perks": ["Gun Nut 1"]
  },
  {
    "name": "Glow Sights (Crossbow)",
    "prefix": "Glow-Sighted",
    "weaponType": "Bow",
    "type": "Sight",
    "rangeChange": 1,
    "gainedQualities": ["Accurate"],
    "weightChange": 1,
    "costChange": 15,
    "perks": ["Gun Nut 2"]
  },
  {
    "name": "Heavy Frame (Crossbow)",
    "prefix": "Heavy",
    "weaponType": "Bow",
    "type": "Frame",
    "damageChange": 1,
    "weightChange": 1,
    "costChange": 30,
    "perks": ["Gun Nut 1"]
  },
  {
    "name": "Repeating Frame (Crossbow)",
    "prefix": "Repeating",
    "weaponType": "Bow",
    "type": "Frame",
    "fireRateChange": 1,
    "gainedQualities": ["Slow Load"],
    "weightChange": 2,
    "costChange": 75,
    "perks": ["Gun Nut 3"]
  },
  {
    "name": "Multiple Launch Frame (Crossbow)",
    "prefix": "Peppered",
    "weaponType": "Bow",
    "type": "Frame",
    "damageChange": -1,
    "gainedEffects": ["Spread"],
    "gainedQualities": ["Ammo-Hungry (3)"],
    "weightChange": 4,
    "costChange": 60,
    "perks": ["Gun Nut 2"]
  },
  {
    "name": "Electrified Blade (Assaultron Blade)",
    "prefix": "Electrified",
    "weaponType": "Melee Weapon",
    "type": "",
    "damageChange": 1,
    "newDamageType": "Energy",
    "weightChange": 0,
    "costChange": 50,
    "perks": ["Blacksmith 2", "Science! 1"]
  },
  {
    "name": "Electrified (Auto-Axe)",
    "prefix": "Electrified",
    "weaponType": "Melee Weapon",
    "type": "",
    "damageChange": 1,
    "newDamageType": "Energy",
    "weightChange": 0,
    "costChange": 50,
    "perks": ["Blacksmith 2", "Science! 1"]
  },
  {
    "name": "Burning (Auto-Axe)",
    "prefix": "Burning",
    "weaponType": "Melee Weapon",
    "type": "",
    "newDamageType": "Energy",
    "gainedEffects": ["Persistent"],
    "weightChange": 0,
    "costChange": 50,
    "perks": ["Blacksmith 2", "Science! 1"]
  },
  {
    "name": "Poisoned (Auto-Axe)",
    "prefix": "Toxic",
    "weaponType": "Melee Weapon",
    "type": "",
    "gainedEffects": ["Persistent (Posion)"],
    "weightChange": 0,
    "costChange": 50,
    "perks": ["Blacksmith 2", "Science! 1"]
  },
  {
    "name": "Turbo (Auto-Axe)",
    "prefix": "Turbo",
    "weaponType": "Melee Weapon",
    "type": "",
    "effects": "Each AP spent for extra damage adds +2CD instead of +1CD.",
    "weightChange": 2,
    "costChange": 50,
    "perks": ["Blacksmith 2", "Science! 1"]
  },
  {
    "name": "Dual Bar (Chainsaw)",
    "prefix": "Dual",
    "weaponType": "Melee Weapon",
    "type": "",
    "damageChange": 2,
    "weightChange": 1,
    "costChange": 30,
    "perks": ["Blacksmith 2"]
  },
  {
    "name": "Bow Bar (Chainsaw)",
    "prefix": "Bow bar",
    "weaponType": "Melee Weapon",
    "type": "",
    "gainedEffects": ["Piercing 1"],
    "weightChange": 2,
    "costChange": 45,
    "perks": ["Blacksmith 3"]
  },
  {
    "name": "Long Bow Bar (Chainsaw)",
    "prefix": "Bow bow bar",
    "weaponType": "Melee Weapon",
    "type": "",
    "gainedEffects": ["Persistent"],
    "weightChange": 3,
    "costChange": 60,
    "perks": ["Blacksmith 3"]
  },
  {
    "name": "Flamer (Chainsaw)",
    "prefix": "Flaming",
    "weaponType": "Melee Weapon",
    "type": "",
    "damageChange": 1,
    "newDamageType": "Energy",
    "weightChange": 0,
    "costChange": 0,
    "perks": []
  }
]
